nested_ragged_tensors/__init__.py
nested_ragged_tensors/ragged_numpy.py
nested_ragged_tensors-0.1.dist-info/LICENSE
nested_ragged_tensors-0.1.dist-info/METADATA
nested_ragged_tensors-0.1.dist-info/WHEEL
nested_ragged_tensors-0.1.dist-info/top_level.txt
nested_ragged_tensors-0.1.dist-info/RECORD
