Metadata-Version: 2.1
Name: nested_ragged_tensors
Version: 0.1
Summary: Utilities for efficiently working with, saving, and loading, collections of connected nested ragged tensors in PyTorch
Author-email: Matthew McDermott <mattmcdermott8@gmail.com>
Project-URL: Homepage, https://github.com/mmcdermott/nested_ragged_tensors
Project-URL: Issues, https://github.com/mmcdermott/nested_ragged_tensors/issues
Classifier: Programming Language :: Python :: 3
Classifier: License :: OSI Approved :: MIT License
Classifier: Operating System :: OS Independent
Requires-Python: >=3.10
License-File: LICENSE
Requires-Dist: safetensors
Requires-Dist: numpy
Provides-Extra: benchmarks
Requires-Dist: ml-mixins; extra == "benchmarks"
Requires-Dist: torch; extra == "benchmarks"
Requires-Dist: rootutils; extra == "benchmarks"
Requires-Dist: memray; extra == "benchmarks"
Provides-Extra: dev
Requires-Dist: pre-commit<4; extra == "dev"
Provides-Extra: docs
Requires-Dist: mkdocs==1.6.0; extra == "docs"
Requires-Dist: mkdocs-material==9.5.31; extra == "docs"
Requires-Dist: mkdocstrings[python,shell]==0.25.2; extra == "docs"
Requires-Dist: mkdocs-gen-files==0.5.0; extra == "docs"
Requires-Dist: mkdocs-literate-nav==0.6.1; extra == "docs"
Requires-Dist: mkdocs-section-index==0.3.9; extra == "docs"
Requires-Dist: mkdocs-git-authors-plugin==0.9.0; extra == "docs"
Requires-Dist: mkdocs-git-revision-date-localized-plugin==1.2.6; extra == "docs"
Provides-Extra: tests
Requires-Dist: pytest; extra == "tests"
Requires-Dist: pytest-cov; extra == "tests"
